{
  "filmes": [
    {
      "titulo": "Murder Mystery",
      "urlFoto": "https://m.media-amazon.com/images/M/MV5BNTA2YTI5YjUtZWI4Zi00NWQ5LWFiYmEtOTBmNTUyNDAwNjllXkEyXkFqcGdeQXVyNjIzNzM4NzA@._V1_UX182_CR0,0,182,268_AL_.jpg",
      "dtLancamento": "2019-06-14T03:00:00.000Z",
      "descricao": "A New York cop and his wife go on a European vacation to reinvigorate the spark in their marriage, but end up getting framed and on the run for the death of an elderly billionaire.",
      "nota": 6,
      "urlIMDb": "https://www.imdb.com/title/tt1618434/?ref_=nv_sr_srsg_3",
      "genero": "Ação",
      "id": 1
    },
    {
      "titulo": "Teste",
      "urlFoto": "",
      "dtLancamento": "2020-04-14T03:00:00.000Z",
      "descricao": "",
      "nota": 0,
      "urlIMDb": "",
      "genero": "Comédia",
      "id": 3
    },
    {
      "titulo": "Teste",
      "urlFoto": "",
      "dtLancamento": "2020-04-08T03:00:00.000Z",
      "descricao": "",
      "nota": 0,
      "urlIMDb": "",
      "genero": "Aventura",
      "id": 6
    }
  ],
  "profile": {
    "name": "typicode"
  }
}